[
  {
    "name": " مخزن التقازي",
    "phone": "+218-21-123-4567",
    "email": "info@takazi-ceramics.ly",
    "address": "طرابلس، ليبيا - سوق الجمعة ",
    "note": "الشركة الأم - مورد رئيسي لجميع منتجات السيراميك والبلاط"
  },
  {
    "name": "مخلص جمركي - شركة الأمان",
    "phone": "+218-91-111-1111",
    "email": "customs@aman-ly.com",
    "address": "طرابلس - ميناء طرابلس البحري",
    "note": "مورد مصروفات جمركية"
  },
  {
    "name": "شركة سفر وسياحة - المسار",
    "phone": "+218-92-222-2222",
    "email": "travel@almasar-ly.com",
    "address": "طرابلس - شارع الجرابة",
    "note": "مورد مصروفات سفر"
  },
  {
    "name": "شركة شحن - المتوسط",
    "phone": "+218-93-333-3333",
    "email": "shipping@med-ly.com",
    "address": "طرابلس - ميناء طرابلس البحري",
    "note": "مورد مصروفات شحن"
  },
  {
    "name": "شركة نقل بري - السريع",
    "phone": "+218-94-444-4444",
    "email": "transport@alsarie-ly.com",
    "address": "طرابلس - طريق الميناء",
    "note": "مورد مصروفات نقل داخلي"
  },
  {
    "name": "شركة خدمات حاويات - الرفع الحديث",
    "phone": "+218-95-555-5555",
    "email": "containers@modernlift-ly.com",
    "address": "طرابلس - الميناء",
    "note": "مورد مصروفات تنزيل من الحاوية"
  },
  {
    "name": "شركة تذاكر سفر - الأفق",
    "phone": "+218-96-666-6666",
    "email": "tickets@alofuq-ly.com",
    "address": "طرابلس - شارع المصيف",
    "note": "مورد تذاكر سفر"
  }
]
